prakriya/__init__.py
prakriya/cli.py
prakriya/generate.py
prakriya/utils.py
prakriya/verbforms.py
prakriya/data/jsonindex.json
prakriya/data/sutrainfo.json
prakriya-0.0.7.dist-info/DESCRIPTION.rst
prakriya-0.0.7.dist-info/METADATA
prakriya-0.0.7.dist-info/RECORD
prakriya-0.0.7.dist-info/WHEEL
prakriya-0.0.7.dist-info/entry_points.txt
prakriya-0.0.7.dist-info/metadata.json
prakriya-0.0.7.dist-info/top_level.txt
