Metadata-Version: 2.0
Name: prakriya
Version: 0.0.7
Summary: prakriya is a package to derive information about given Sanskrit verb form.
Home-page: https://github.com/drdhaval2785/python-prakriya
Author: Dr. Dhaval Patel
Author-email: drdhaval2785@gmail.com
License: GNU General Public License v3
Keywords: prakriya,panini,Sanskrit,grammar,tinanta
Platform: UNKNOWN
Classifier: Development Status :: 2 - Pre-Alpha
Classifier: Intended Audience :: Developers
Classifier: License :: OSI Approved :: GNU General Public License v3 (GPLv3)
Classifier: Programming Language :: Python :: 2
Classifier: Programming Language :: Python :: 2.7
Classifier: Programming Language :: Python :: 3
Classifier: Programming Language :: Python :: 3.6
Classifier: Programming Language :: Python :: 3.5
Classifier: Programming Language :: Python :: 3.4
Classifier: Programming Language :: Python :: 3.3
Requires-Dist: Click (>=6.0)
Requires-Dist: requests
Requires-Dist: indic-transliteration
